Metadata-Version: 2.1
Name: pygmy-url
Version: 2.0.4
Summary: URL shortener built in flask
Home-page: https://github.com/kellya/pygmy
Author: Alex Kelly
Author-email: alex.kelly@franklin.edu
License: MIT
Keywords: url shortener flask
Platform: UNKNOWN
Classifier: Development Status :: 5 - Production/Stable
Classifier: Framework :: Flask
Classifier: Environment :: Console
Classifier: Intended Audience :: Developers
Classifier: Operating System :: OS Independent
Classifier: Programming Language :: Python
